{ "type": "FeatureCollection", "crs": { "type": "name", "properties": { "name": "urn:ogc:def:crs:OGC:1.3:CRS84" } }, "features": [ 
{ "type": "Feature", "properties": { "Name": "William Falk-Wallace", "Description": "Sat Nov  9 12:12:51 EST 2013; Location Accuracy: 65.000000" }, "geometry": { "type": "Point", "coordinates": [ -73.961253, 40.809414, 0.0 ] } },
<<<<<<< HEAD
{ "type": "Feature", "properties": { "Name": "William Falk-Wallace", "Description": "Sat Nov  9 12:12:23 EST 2013; Location Accuracy: 65.000000" }, "geometry": { "type": "Point", "coordinates": [ -73.961253, 40.809414, 0.0 ] } },
{ "type": "Feature", "properties": { "Name": "William Falk-Wallace", "Description": "Sat Nov  9 12:12:03 EST 2013; Location Accuracy: 65.000000" }, "geometry": { "type": "Point", "coordinates": [ -73.961253, 40.809414, 0.0 ] } },
{ "type": "Feature", "properties": { "Name": "William Falk-Wallace", "Description": "Sat Nov  9 12:11:23 EST 2013; Location Accuracy: 65.000000" }, "geometry": { "type": "Point", "coordinates": [ -73.961253, 40.809414, 0.0 ] } },
=======
{ "type": "Feature", "properties": { "Name": "Thomas", "Description": "Sat Nov  9 12:10:37 EST 2013; Location Accuracy: 65.000000" }, "geometry": { "type": "Point", "coordinates": [ -73.961237, 40.809414, 0.0 ] } },
>>>>>>> 92988a6a92b9a0443878f4452e615a6977e21c08
{ "type": "Feature", "properties": { "Name": "Thomas", "Description": "Fri Nov  8 17:29:34 EST 2013; Location Accuracy: it" }, "geometry": { "type": "Point", "coordinates": [ enabled., is, 0.0 ] } },
{ "type": "Feature", "properties": { "Name": "Thomas", "Description": "Fri Nov  8 17:20:15 EST 2013; Location Accuracy: it" }, "geometry": { "type": "Point", "coordinates": [ enabled., is, 0.0 ] } },
{ "type": "Feature", "properties": { "Name": "Thomas", "Description": "Wed Nov  6 22:28:10 EST 2013; Location Accuracy: 65.000000" }, "geometry": { "type": "Point", "coordinates": [ -73.959969, 40.807971, 0.0 ] } },
{ "type": "Feature", "properties": { "Name": "Thomas", "Description": "Wed Nov  6 22:22:45 EST 2013; Location Accuracy: 65.000000" }, "geometry": { "type": "Point", "coordinates": [ -73.960012, 40.807963, 0.0 ] } },
{ "type": "Feature", "properties": { "Name": "Thomas", "Description": "Wed Nov  6 22:17:35 EST 2013; Location Accuracy: 65.000000" }, "geometry": { "type": "Point", "coordinates": [ -73.959945, 40.807986, 0.0 ] } },
{ "type": "Feature", "properties": { "Name": "Thomas", "Description": "Wed Nov  6 22:16:37 EST 2013; Location Accuracy: 65.000000" }, "geometry": { "type": "Point", "coordinates": [ -73.960020, 40.807996, 0.0 ] } },
{ "type": "Feature", "properties": { "Name": "William Falk-Wallace", "Description": "Wed Nov  6 19:35:21 EST 2013; Location Accuracy: 99.999998" }, "geometry": { "type": "Point", "coordinates": [ -73.963082, 40.809966, 0.0 ] } },
{ "type": "Feature", "properties": { "Name": "Thomas", "Description": "Sun Nov  3 17:56:57 EST 2013; Location Accuracy: 65.000000" }, "geometry": { "type": "Point", "coordinates": [ -73.961698, 40.809968, 0.0 ] } },
{ "type": "Feature", "properties": { "Name": "Thomas", "Description": "Sun Nov  3 15:26:53 EST 2013; Location Accuracy: 65.000000" }, "geometry": { "type": "Point", "coordinates": [ -73.959872, 40.807931, 0.0 ] } },
{ "type": "Feature", "properties": { "Name": "Thomas", "Description": "Fri Nov  1 15:48:48 EDT 2013; Location Accuracy: 91.030605" }, "geometry": { "type": "Point", "coordinates": [ -73.961202, 40.809398, 0.0 ] } },
{ "type": "Feature", "properties": { "Name": "Thomas", "Description": "Fri Nov  1 15:45:30 EDT 2013; Location Accuracy: 91.030605" }, "geometry": { "type": "Point", "coordinates": [ -73.961202, 40.809398, 0.0 ] } },
{ "type": "Feature", "properties": { "Name": "Thomas", "Description": "Fri Nov  1 15:43:32 EDT 2013; Location Accuracy: 91.030605" }, "geometry": { "type": "Point", "coordinates": [ -73.961202, 40.809398, 0.0 ] } },
{ "type": "Feature", "properties": { "Name": "William Falk-Wallace", "Description": "Fri Nov  1 15:33:33 EDT 2013; Location Accuracy: 65.000000" }, "geometry": { "type": "Point", "coordinates": [ -73.961264, 40.809404, 0.0 ] } },
{ "type": "Feature", "properties": { "Name": "William Falk-Wallace", "Description": "Fri Nov  1 15:24:35 EDT 2013; Location Accuracy: 65.000000" }, "geometry": { "type": "Point", "coordinates": [ -73.961250, 40.809416, 0.0 ] } },
{ "type": "Feature", "properties": { "Name": "William Falk-Wallace", "Description": "Fri Nov  1 15:00:57 EDT 2013; Location Accuracy: 65.000000" }, "geometry": { "type": "Point", "coordinates": [ -73.961267, 40.809411, 0.0 ] } }
]}
