s
{ "type": "Feature", "properties": { "Name": "William Falk-Wallace", "Description": "Wed Dec 18 15:10:37 EST 2013; Location Accuracy: 65.000000" }, "geometry": { "type": "Point", "coordinates": [ -73.969687, 40.800792, 0.0 ] } },
